package_smoke_test/__main__.py
package_smoke_test-1.0.dist-info/LICENSE.GPL-3
package_smoke_test-1.0.dist-info/METADATA
package_smoke_test-1.0.dist-info/WHEEL
package_smoke_test-1.0.dist-info/top_level.txt
package_smoke_test-1.0.dist-info/RECORD
