Metadata-Version: 2.1
Name: package-smoke-test
Version: 1.0
Summary: Simple import test for Python packages
Author-email: Ben Finney <ben+python@benfinney.id.au>
Project-URL: Homepage, https://salsa.debian.org/bignose/python-package-smoke-test/
Project-URL: Issue tracker, https://bugs.debian.org/
Project-URL: Change log, https://salsa.debian.org/bignose/python-package-smoke-test/-/raw/main/ChangeLog
Keywords: test,smoke,packaging
Classifier: Development Status :: 5 - Production/Stable
Classifier: License :: OSI Approved :: GNU General Public License v3 or later (GPLv3+)
Classifier: Operating System :: POSIX
Classifier: Programming Language :: Python :: 3
Classifier: Intended Audience :: Developers
Classifier: Topic :: Software Development :: Testing
Requires-Python: >=3.7
License-File: LICENSE.GPL-3
